sourcery_rules_generator/__init__.py
sourcery_rules_generator/__main__.py
sourcery_rules_generator/cli/__init__.py
sourcery_rules_generator/cli/cli.py
sourcery_rules_generator/cli/dependencies_cli.py
sourcery_rules_generator/cli/expensive_loop_cli.py
sourcery_rules_generator/cli/voldemort_cli.py
sourcery_rules_generator/dependencies.py
sourcery_rules_generator/expensive_loop.py
sourcery_rules_generator/models.py
sourcery_rules_generator/voldemort.py
sourcery_rules_generator/yaml_converter.py
sourcery_rules_generator-0.6.1.dist-info/entry_points.txt
sourcery_rules_generator-0.6.1.dist-info/WHEEL
sourcery_rules_generator-0.6.1.dist-info/METADATA
sourcery_rules_generator-0.6.1.dist-info/RECORD
