Metadata-Version: 2.1
Name: sourcery-rules-generator
Version: 0.6.1
Summary: Generate architecture rules for Python projects.
Home-page: https://github.com/sourcery-ai/sourcery-rules-generator
License: MIT
Keywords: architecture,development
Author: reka
Author-email: reka@sourcery.ai
Requires-Python: >=3.9,<4.0
Classifier: Intended Audience :: Developers
Classifier: License :: OSI Approved :: MIT License
Classifier: Programming Language :: Python :: 3
Classifier: Programming Language :: Python :: 3.9
Classifier: Programming Language :: Python :: 3.10
Classifier: Programming Language :: Python :: 3.11
Classifier: Topic :: Software Development
Classifier: Topic :: Software Development :: Libraries :: Python Modules
Requires-Dist: pydantic (>=1.10.2,<2.0.0)
Requires-Dist: rich (>=12.6.0,<13.0.0)
Requires-Dist: ruamel-yaml (>=0.17.21,<0.18.0)
Requires-Dist: typer[all] (==0.7.0)
Project-URL: Repository, https://github.com/sourcery-ai/sourcery-rules-generator
